logging_error_custom/__init__.py
logging_error_custom/logger.py
logging_error_custom-0.13.dist-info/METADATA
logging_error_custom-0.13.dist-info/WHEEL
logging_error_custom-0.13.dist-info/top_level.txt
logging_error_custom-0.13.dist-info/RECORD
